health_indices/__init__.py
health_indices/health_indices.py
health_indices-0.0.1.dist-info/WHEEL
health_indices-0.0.1.dist-info/METADATA
health_indices-0.0.1.dist-info/RECORD
