Metadata-Version: 2.1
Name: health-indices
Version: 0.0.1
Summary: a unified collection of health indices and indicators eg bmi,bai,etc
Home-page: https://github.com/jcharistech/health-indices
License: MIT
Keywords: health-indices,health-indicators,bmi,bodymass index,bai,birth-rate,jcharistech
Author: Jesse E.Agbe(JCharis)
Author-email: jcharistech@gmail.com
Requires-Python: >=3.8,<4.0
Classifier: License :: OSI Approved :: MIT License
Classifier: Operating System :: OS Independent
Classifier: Programming Language :: Python :: 3
Classifier: Programming Language :: Python :: 3.6
Classifier: Programming Language :: Python :: 3.7
Classifier: Programming Language :: Python :: 3.8
Classifier: Programming Language :: Python :: 3.9
Project-URL: Repository, https://github.com/jcharistech/health-indices
